{
    "Ar36": {
        "error": 0.0018356780624344381,
        "error_type": "SEM",
        "filter_outliers_dict": {
            "filter_outliers": true,
            "iterations": 1,
            "std_devs": 3,
            "use_iqr_filtering": false,
            "use_standard_deviation_filtering": false
        },
        "fit": "linear",
        "fn": 339,
        "include_baseline_error": false,
        "n": 340,
        "outlier_excluded": [
            311
        ],
        "reviewed": true,
        "user_excluded": [],
        "value": 1.6266755043388126
    },
    "Ar37": {
        "error": 0.01573329065185157,
        "error_type": "SEM",
        "filter_outliers_dict": {
            "filter_outliers": true,
            "iterations": 1,
            "std_devs": 3,
            "use_iqr_filtering": false,
            "use_standard_deviation_filtering": false
        },
        "fit": "linear",
        "fn": 337,
        "include_baseline_error": false,
        "n": 340,
        "outlier_excluded": [
            81,
            73,
            117
        ],
        "reviewed": true,
        "user_excluded": [],
        "value": 1.3236411953615903
    },
    "Ar38": {
        "error": 0.005452924886584879,
        "error_type": "SEM",
        "filter_outliers_dict": {
            "filter_outliers": true,
            "iterations": 1,
            "std_devs": 3,
            "use_iqr_filtering": false,
            "use_standard_deviation_filtering": false
        },
        "fit": "linear",
        "fn": 340,
        "include_baseline_error": false,
        "n": 340,
        "outlier_excluded": [],
        "reviewed": true,
        "user_excluded": [],
        "value": 2.1943739757005982
    },
    "Ar39": {
        "error": 0.023228736947865994,
        "error_type": "SEM",
        "filter_outliers_dict": {
            "filter_outliers": true,
            "iterations": 1,
            "std_devs": 3,
            "use_iqr_filtering": false,
            "use_standard_deviation_filtering": false
        },
        "fit": "parabolic",
        "fn": 340,
        "include_baseline_error": false,
        "n": 340,
        "outlier_excluded": [],
        "reviewed": true,
        "user_excluded": [],
        "value": 75.29374191138463
    },
    "Ar40": {
        "error": 0.09284572259253936,
        "error_type": "SEM",
        "filter_outliers_dict": {
            "filter_outliers": true,
            "iterations": 1,
            "std_devs": 3,
            "use_iqr_filtering": false,
            "use_standard_deviation_filtering": false
        },
        "fit": "parabolic",
        "fn": 334,
        "include_baseline_error": false,
        "n": 340,
        "outlier_excluded": [
            262,
            88,
            89,
            90,
            252,
            253
        ],
        "reviewed": true,
        "user_excluded": [],
        "value": 902.9058034809815
    }
}